MANIFEST.in
README.txt
setup.cfg
setup.py
test.ini
ontosrv.egg-info/PKG-INFO
ontosrv.egg-info/SOURCES.txt
ontosrv.egg-info/dependency_links.txt
ontosrv.egg-info/entry_points.txt
ontosrv.egg-info/not-zip-safe
ontosrv.egg-info/paster_plugins.txt
ontosrv.egg-info/requires.txt
ontosrv.egg-info/top_level.txt
ordf/__init__.py
ordf/onto/__init__.py
ordf/onto/websetup.py
ordf/onto/config/__init__.py
ordf/onto/config/deployment.ini_tmpl
ordf/onto/config/environment.py
ordf/onto/config/middleware.py
ordf/onto/config/routing.py
ordf/onto/controllers/__init__.py
ordf/onto/controllers/error.py
ordf/onto/controllers/graph.py
ordf/onto/controllers/home.py
ordf/onto/controllers/sparql.py
ordf/onto/lib/__init__.py
ordf/onto/lib/app_globals.py
ordf/onto/lib/base.py
ordf/onto/lib/helpers.py
ordf/onto/model/__init__.py
ordf/onto/n3/changeset.n3
ordf/onto/n3/doap.n3
ordf/onto/n3/foaf.n3
ordf/onto/n3/fresnel.n3
ordf/onto/n3/ontology.n3
ordf/onto/n3/rdfs.n3
ordf/onto/n3/sdmx.n3
ordf/onto/n3/void.n3
ordf/onto/public/bg.png
ordf/onto/public/favicon.ico
ordf/onto/public/pylons-logo.gif
ordf/onto/public/css/fresnel.css
ordf/onto/public/css/sdmx.css
ordf/onto/templates/__init__.py
ordf/onto/templates/base.html
ordf/onto/templates/error.html
ordf/onto/templates/graph.html
ordf/onto/templates/sparql_html.html
ordf/onto/templates/sparql_json.html
ordf/onto/tests/__init__.py
ordf/onto/tests/test_models.py
ordf/onto/tests/functional/__init__.py
ordf/onto/tests/functional/test_graph.py