Metadata-Version: 1.0
Name: ontosrv
Version: 0.8
Summary: ORDF Ontology Service
Home-page: UNKNOWN
Author: William Waites
Author-email: william.waites_at_okfn.org
License: UNKNOWN
Platform: UNKNOWN
